kedo_pex-1.2.7.0.dist-info/DESCRIPTION.rst
kedo_pex-1.2.7.0.dist-info/METADATA
kedo_pex-1.2.7.0.dist-info/RECORD
kedo_pex-1.2.7.0.dist-info/WHEEL
kedo_pex-1.2.7.0.dist-info/entry_points.txt
kedo_pex-1.2.7.0.dist-info/metadata.json
kedo_pex-1.2.7.0.dist-info/top_level.txt
kedo_pex-1.2.7.0.dist-info/zip-safe
pex/__init__.py
pex/archiver.py
pex/base.py
pex/common.py
pex/compatibility.py
pex/compiler.py
pex/crawler.py
pex/environment.py
pex/executor.py
pex/fetcher.py
pex/finders.py
pex/glibc.py
pex/http.py
pex/installer.py
pex/interpreter.py
pex/iterator.py
pex/link.py
pex/orderedset.py
pex/package.py
pex/pep425tags.py
pex/pex.py
pex/pex_bootstrapper.py
pex/pex_builder.py
pex/pex_info.py
pex/requirements.py
pex/resolvable.py
pex/resolver.py
pex/resolver_options.py
pex/sorter.py
pex/testing.py
pex/tracer.py
pex/translator.py
pex/util.py
pex/variables.py
pex/version.py
pex/bin/__init__.py
pex/bin/pex.py
pex/commands/__init__.py
pex/commands/bdist_pex.py
